wotplot/__init__.py
wotplot/_logging.py
wotplot/_make.py
wotplot/_matrix.py
wotplot/_scipy_sm_constructor_getter.py
wotplot/_version.py
wotplot/_viz.py
wotplot-0.4.0.dist-info/LICENSE
wotplot-0.4.0.dist-info/METADATA
wotplot-0.4.0.dist-info/WHEEL
wotplot-0.4.0.dist-info/top_level.txt
wotplot-0.4.0.dist-info/RECORD
