Metadata-Version: 2.1
Name: wotplot
Version: 0.4.0
Summary: Small library for creating and visualizing dot plot matrices
Home-page: https://github.com/fedarko/wotplot
Author: Marcus Fedarko
Author-email: mfedarko@ucsd.edu
Maintainer: Marcus Fedarko
Maintainer-email: mfedarko@ucsd.edu
License: BSD
Platform: UNKNOWN
Classifier: Development Status :: 3 - Alpha
Classifier: License :: OSI Approved :: BSD License
Classifier: Topic :: Scientific/Engineering
Classifier: Topic :: Scientific/Engineering :: Bio-Informatics
Classifier: Topic :: Scientific/Engineering :: Visualization
Classifier: Programming Language :: Python :: 3 :: Only
Classifier: Operating System :: Unix
Classifier: Operating System :: POSIX
Classifier: Operating System :: MacOS :: MacOS X
Requires-Python: >=3.6
License-File: LICENSE
Requires-Dist: numpy
Requires-Dist: scipy (>=0.9)
Requires-Dist: matplotlib
Requires-Dist: pydivsufsort
Provides-Extra: dev
Requires-Dist: pytest (>=4.2) ; extra == 'dev'
Requires-Dist: pytest-cov (>=2.0) ; extra == 'dev'
Requires-Dist: pytest-mock ; extra == 'dev'
Requires-Dist: flake8 ; extra == 'dev'
Requires-Dist: black (<22.10) ; extra == 'dev'
